pysmvr/__init__.py
pysmvr/__main__.py
pysmvr/core.py
pysmvr-0.0.6.dist-info/METADATA
pysmvr-0.0.6.dist-info/RECORD
pysmvr-0.0.6.dist-info/WHEEL
pysmvr-0.0.6.dist-info/entry_points.txt
pysmvr-0.0.6.dist-info/top_level.txt
